{
  "nom": "État de mal épileptique",
  "description": "Prise en charge de l'état de mal épileptique chez l'enfant",
  "etapes": [
    {
      "titre": "Mesures générales immédiates",
      "temps": "T0",
      "elements": [
        {
          "type": "texte",
          "texte": "• Position latérale de sécurité\n• Libération des voies aériennes\n• Oxygénothérapie au masque (6-10 L/min)\n• Monitorage: SpO2, FC, PA, scope\n• Glycémie capillaire\n• Voie veineuse périphérique\n• Chronomètre"
        }
      ],
      "attention": "Ne jamais forcer l'ouverture de la bouche pendant la crise"
    },
    {
      "titre": "Midazolam intrabuccal ou intranasal",
      "temps": "T0-T5",
      "elements": [
        {
          "type": "texte",
          "texte": "Si pas de voie veineuse:"
        },
        {
          "type": "medicament",
          "medicament": {
            "nom": "Midazolam",
            "indication": "Convulsions",
            "voie": "Intranasale"
          }
        },
        {
          "type": "texte",
          "texte": "Buccal: entre la gencive et la joue\nIntranasal: 0.2-0.3 mL par narine"
        }
      ],
      "attention": "Privilégier la voie IV si disponible"
    },
    {
      "titre": "Benzodiazépine IV - 1ère dose",
      "temps": "T5",
      "elements": [
        {
          "type": "texte",
          "texte": "Au choix:"
        },
        {
          "type": "medicament",
          "medicament": {
            "nom": "Midazolam",
            "indication": "Convulsions",
            "voie": "IV"
          }
        },
        {
          "type": "texte",
          "texte": "\nSi convulsions persistent après 5 min → étape suivante"
        }
      ],
      "attention": "Surveillance respiratoire stricte - Préparer matériel de ventilation"
    },
    {
      "titre": "Benzodiazépine IV - 2ème dose",
      "temps": "T10",
      "elements": [
        {
          "type": "texte",
          "texte": "Répéter la même dose:"
        },
        {
          "type": "medicament",
          "medicament": {
            "nom": "Midazolam",
            "indication": "Convulsions",
            "voie": "IV"
          }
        },
        {
          "type": "texte",
          "texte": "\nSi convulsions persistent après 5 min → étape suivante"
        }
      ],
      "attention": "Risque majeur de dépression respiratoire - Préparer l'intubation"
    },
    {
      "titre": "Antiépileptique de 2ème ligne",
      "temps": "T15-T20",
      "elements": [
        {
          "type": "texte",
          "texte": "Au choix:\n\n• Phénytoïne (Dilantin) 20 mg/kg IV en 20 min\n  - Diluer dans NaCl 0.9% uniquement\n  - Perfusion lente avec scope ECG\n\n• OU Lévétiracétam (Keppra) 40 mg/kg IV en 15 min (max 3000 mg)\n\n• OU Valproate de sodium 40 mg/kg IV en 5 min (max 3000 mg)"
        }
      ],
      "attention": "Phénytoïne CI si trouble de conduction - Pas dans G5%"
    },
    {
      "titre": "État de mal réfractaire",
      "temps": "> T20",
      "elements": [
        {
          "type": "texte",
          "texte": "⚠️ Appel réanimation pédiatrique URGENT\n\nPerfusion continue d'un des:\n• Midazolam 0.2 mg/kg bolus puis 0.1-0.4 mg/kg/h\n• Propofol 2 mg/kg bolus puis 5-10 mg/kg/h\n• Thiopental 3-5 mg/kg bolus puis 3-5 mg/kg/h\n\nIntubation + ventilation mécanique\nEEG continu"
        }
      ],
      "attention": "Transfert en réanimation obligatoire - Anesthésie requise"
    },
    {
      "titre": "Bilan étiologique",
      "elements": [
        {
          "type": "texte",
          "texte": "• NFS, CRP, ionogramme sanguin, calcémie, magnésémie\n• Glycémie, lactates\n• Bilan hépatique et rénal\n• Gaz du sang\n• Dosage antiépileptiques si traitement\n• PL si fièvre (après stabilisation)\n• TDM cérébral si indication\n• Recherche toxiques si contexte"
        }
      ]
    }
  ]
}
